trspectrometer/__init__.py
trspectrometer/__main__.py
trspectrometer/aboutpanel.py
trspectrometer/aboutpanel.ui
trspectrometer/busydialog.py
trspectrometer/configuration.py
trspectrometer/datapanel.py
trspectrometer/datapanel.ui
trspectrometer/datapanelscans.ui
trspectrometer/datastorage.py
trspectrometer/hardware.py
trspectrometer/logpanel.py
trspectrometer/logpanel.ui
trspectrometer/mainwindow.py
trspectrometer/mainwindow.ui
trspectrometer/qtwidgets.py
trspectrometer/signalstorage.py
trspectrometer/trspectrometer_rc.py
trspectrometer/ufsfile.py
trspectrometer/utils.py
trspectrometer/plugins/__init__.py
trspectrometer/plugins/acquisition/__init__.py
trspectrometer/plugins/acquisition/ta_dummy.py
trspectrometer/plugins/acquisition/ta_stepped.py
trspectrometer/plugins/acquisition/ta_swept.py
trspectrometer/plugins/aligncam/__init__.py
trspectrometer/plugins/aligncam/alignmentpanel.py
trspectrometer/plugins/aligncam/alignmentpanel.ui
trspectrometer/plugins/aligncam/cv2camera.py
trspectrometer/plugins/chopper/__init__.py
trspectrometer/plugins/chopper/dummychopper.py
trspectrometer/plugins/chopper/thorlabs_mc2000b.py
trspectrometer/plugins/delay/__init__.py
trspectrometer/plugins/delay/dummydelay.py
trspectrometer/plugins/delay/thorlabs_apt.py
trspectrometer/plugins/detector/__init__.py
trspectrometer/plugins/detector/dummydetector.py
trspectrometer/plugins/detector/zylafixed.py
trspectrometer/plugins/interface/__init__.py
trspectrometer/plugins/interface/dummyinterface.py
trspectrometer/plugins/interface/trsi.py
trspectrometer/plugins/repratemenu/__init__.py
trspectrometer/plugins/scope/__init__.py
trspectrometer/plugins/scope/scopepanel.py
trspectrometer/plugins/scope/scopepanel.ui
trspectrometer/plugins/zylaalign/__init__.py
trspectrometer/plugins/zylaalign/zylaalignpanel.py
trspectrometer/plugins/zylaalign/zylaalignpanel.ui
trspectrometer-1.2.3.dist-info/LICENSE.txt
trspectrometer-1.2.3.dist-info/METADATA
trspectrometer-1.2.3.dist-info/WHEEL
trspectrometer-1.2.3.dist-info/entry_points.txt
trspectrometer-1.2.3.dist-info/top_level.txt
trspectrometer-1.2.3.dist-info/RECORD
