Metadata-Version: 2.1
Name: trspectrometer
Version: 1.2.3
Summary: Software for running a time-resolved spectrometer.
Home-page: https://gitlab.com/ptapping/trspectrometer
Author: Patrick Tapping
Author-email: mail@patricktapping.com
Project-URL: Documentation, https://trspectrometer.readthedocs.io/
Project-URL: Source, https://gitlab.com/ptapping/trspectrometer
Project-URL: Tracker, https://gitlab.com/ptapping/trspectrometer/-/issues
Classifier: Programming Language :: Python :: 3
Classifier: License :: OSI Approved :: GNU General Public License v3 or later (GPLv3+)
Classifier: Operating System :: OS Independent
Requires-Python: >=3.7
License-File: LICENSE.txt
Requires-Dist: PySide6
Requires-Dist: pyqtgraph
Requires-Dist: numpy
Requires-Dist: scipy
Requires-Dist: opencv-python-headless
Requires-Dist: tomlkit
Requires-Dist: appdirs
Requires-Dist: zarr
Requires-Dist: pyreadline
Requires-Dist: pluginlib
Requires-Dist: thorlabs-apt-device
Requires-Dist: thorlabs-mc2000b
Requires-Dist: andor3
Requires-Dist: trs-interface
